homeassistant_historical_sensor/__init__.py
homeassistant_historical_sensor/consts.py
homeassistant_historical_sensor/patches.py
homeassistant_historical_sensor/recorderutil.py
homeassistant_historical_sensor/sensor.py
homeassistant_historical_sensor/state.py
homeassistant_historical_sensor-1.0.1.dist-info/METADATA
homeassistant_historical_sensor-1.0.1.dist-info/WHEEL
homeassistant_historical_sensor-1.0.1.dist-info/top_level.txt
homeassistant_historical_sensor-1.0.1.dist-info/RECORD
