Metadata-Version: 2.1
Name: homeassistant-historical-sensor
Version: 1.0.1
Summary: Historical sensors for HomeAssistant
Home-page: https://github.com/ldotlopez/ha-historical-sensor
Author: Luis López
Author-email: luis@cuarentaydos.com
Project-URL: Repository, https://github.com/ldotlopez/ha-historical-sensor/
Project-URL: Bug Tracker, https://github.com/ldotlopez/ha-historical-sensor/issues
Requires-Python: >=3.9
